{
    "first_theme": "10. Классификация и номенклатура органических веществ",
    "second_theme": "11. Теория строения органических соединений. Типы связей в молекулах органических веществ",
    "third_theme": "12. Характерные химические свойства",
    "fourth_theme": "13. Свойства азотсодержащих органических соединений",
    "fifth_theme": "14. Характерные химические свойства углеводородов. Механизмы реакций",
    "sixth_theme": "15. Свой­ства спиртов, альдегидов, кислот, слож­ных эфиров, фенола",
    "seventh_theme": "16. Взаимосвязь углеводородов и кислородосодержащих органических соединений",
    "eighth_theme": "32. Взаимосвязь органических соединений"
}